[   
     {
        "taskCounter": 3188,
        "typeTask": 1,
        "taskKec": [1, 1, 1],
        "taskAnswer": [235, 192.5, 6.3, 685.9, 1.9],
        "task": 11,
        "task1": [16, 17, 18, 215, 225, 235
        , "215/65", "215/60", "—"
        , "225/65; 225/60", "225/55", "—"
        , "235/60", "235/55; 235/50", "235/50"],

        "task2": "Сколько миллиметров составляет высота боковины шины, имеющей маркировку 275/70 R16?",
        "task3": "На сколько миллиметров увеличится диаметр колеса, если заменить колёса, установленные на заводе, колёсами с шинами 235/50 R18?",
        "task4": "Найдите диаметр колеса автомобиля, выходящего с завода. Ответ дайте в миллиметрах.",
        "task5": "На сколько процентов увеличится пробег автомобиля при одном обороте колеса, если заменить колёса, установленные на заводе, колёсами с шинами 225/65 R16? Результат округлите до десятых.",

        "task6": ["F2EFEB", "4AE379", "0C1C4B", "1FDDE9", "AEDE0E"],
        "task7": [1, 2, 3, 4, 5],
        "taskNum": "07BC41"
    }
]